{
   "runs" : [
      {
         "OS" : "linux",
         "abstract" : "Validates a set of parameters against a schema",
         "dir" : "/home/runner/work/Params-Validate-Strict/Params-Validate-Strict",
         "finish" : 1761250675.79415,
         "name" : "Params-Validate-Strict",
         "perl" : "5.40.3",
         "run" : "-e",
         "start" : 1761250675.79386,
         "version" : "0.20"
      },
      {
         "OS" : "linux",
         "abstract" : "Validates a set of parameters against a schema",
         "dir" : "/home/runner/work/Params-Validate-Strict/Params-Validate-Strict",
         "finish" : 1761250675.95431,
         "name" : "Params-Validate-Strict",
         "perl" : "5.40.3",
         "run" : "-e",
         "start" : 1761250675.95413,
         "version" : "0.20"
      },
      {
         "OS" : "linux",
         "abstract" : "Validates a set of parameters against a schema",
         "dir" : "/home/runner/work/Params-Validate-Strict/Params-Validate-Strict",
         "finish" : 1761250676.11378,
         "name" : "Params-Validate-Strict",
         "perl" : "5.40.3",
         "run" : "-e",
         "start" : 1761250676.11351,
         "version" : "0.20"
      },
      {
         "OS" : "linux",
         "abstract" : "Validates a set of parameters against a schema",
         "dir" : "/home/runner/work/Params-Validate-Strict/Params-Validate-Strict",
         "finish" : 1761250676.27273,
         "name" : "Params-Validate-Strict",
         "perl" : "5.40.3",
         "run" : "-e",
         "start" : 1761250676.27246,
         "version" : "0.20"
      },
      {
         "OS" : "linux",
         "abstract" : "Validates a set of parameters against a schema",
         "dir" : "/home/runner/work/Params-Validate-Strict/Params-Validate-Strict",
         "finish" : 1761250676.43132,
         "name" : "Params-Validate-Strict",
         "perl" : "5.40.3",
         "run" : "-e",
         "start" : 1761250676.43115,
         "version" : "0.20"
      },
      {
         "OS" : "linux",
         "abstract" : "Validates a set of parameters against a schema",
         "dir" : "/home/runner/work/Params-Validate-Strict/Params-Validate-Strict",
         "finish" : 1761250676.59068,
         "name" : "Params-Validate-Strict",
         "perl" : "5.40.3",
         "run" : "-e",
         "start" : 1761250676.5905,
         "version" : "0.20"
      },
      {
         "OS" : "linux",
         "abstract" : "Validates a set of parameters against a schema",
         "dir" : "/home/runner/work/Params-Validate-Strict/Params-Validate-Strict",
         "finish" : 1761250676.75099,
         "name" : "Params-Validate-Strict",
         "perl" : "5.40.3",
         "run" : "-e",
         "start" : 1761250676.75081,
         "version" : "0.20"
      },
      {
         "OS" : "linux",
         "abstract" : "Validates a set of parameters against a schema",
         "dir" : "/home/runner/work/Params-Validate-Strict/Params-Validate-Strict",
         "finish" : 1761250676.91023,
         "name" : "Params-Validate-Strict",
         "perl" : "5.40.3",
         "run" : "-e",
         "start" : 1761250676.91006,
         "version" : "0.20"
      },
      {
         "OS" : "linux",
         "abstract" : "Validates a set of parameters against a schema",
         "dir" : "/home/runner/work/Params-Validate-Strict/Params-Validate-Strict",
         "finish" : 1761250677.08705,
         "name" : "Params-Validate-Strict",
         "perl" : "5.40.3",
         "run" : "-e",
         "start" : 1761250677.07669,
         "version" : "0.20"
      },
      {
         "OS" : "linux",
         "abstract" : "Validates a set of parameters against a schema",
         "dir" : "/home/runner/work/Params-Validate-Strict/Params-Validate-Strict",
         "finish" : 1761250687.18495,
         "name" : "Params-Validate-Strict",
         "perl" : "5.40.3",
         "run" : "-e",
         "start" : 1761250677.27725,
         "version" : "0.20"
      },
      {
         "OS" : "linux",
         "abstract" : "Validates a set of parameters against a schema",
         "dir" : "/home/runner/work/Params-Validate-Strict/Params-Validate-Strict",
         "finish" : 1761250677.41858,
         "name" : "Params-Validate-Strict",
         "perl" : "5.40.3",
         "run" : "-e",
         "start" : 1761250677.41849,
         "version" : "0.20"
      },
      {
         "OS" : "linux",
         "abstract" : "Validates a set of parameters against a schema",
         "dir" : "/home/runner/work/Params-Validate-Strict/Params-Validate-Strict",
         "finish" : 1761250677.68069,
         "name" : "Params-Validate-Strict",
         "perl" : "5.40.3",
         "run" : "t/00-load.t",
         "start" : 1761250677.6798,
         "version" : "0.20"
      },
      {
         "OS" : "linux",
         "abstract" : "Validates a set of parameters against a schema",
         "dir" : "/home/runner/work/Params-Validate-Strict/Params-Validate-Strict",
         "finish" : 1761250678.19271,
         "name" : "Params-Validate-Strict",
         "perl" : "5.40.3",
         "run" : "t/10-compile.t",
         "start" : 1761250678.03671,
         "version" : "0.20"
      },
      {
         "OS" : "linux",
         "abstract" : "Validates a set of parameters against a schema",
         "dir" : "/home/runner/work/Params-Validate-Strict/Params-Validate-Strict",
         "finish" : 1761250678.49174,
         "name" : "Params-Validate-Strict",
         "perl" : "5.40.3",
         "run" : "t/30-basics.t",
         "start" : 1761250678.46374,
         "version" : "0.20"
      },
      {
         "OS" : "linux",
         "abstract" : "Validates a set of parameters against a schema",
         "dir" : "/home/runner/work/Params-Validate-Strict/Params-Validate-Strict",
         "finish" : 1761250679.03789,
         "name" : "Params-Validate-Strict",
         "perl" : "5.40.3",
         "run" : "t/40-more.t",
         "start" : 1761250678.91566,
         "version" : "0.20"
      },
      {
         "OS" : "linux",
         "abstract" : "Validates a set of parameters against a schema",
         "dir" : "/home/runner/work/Params-Validate-Strict/Params-Validate-Strict",
         "finish" : 1761250679.6851,
         "name" : "Params-Validate-Strict",
         "perl" : "5.40.3",
         "run" : "t/50-even-more.t",
         "start" : 1761250679.64599,
         "version" : "0.20"
      },
      {
         "OS" : "linux",
         "abstract" : "Validates a set of parameters against a schema",
         "dir" : "/home/runner/work/Params-Validate-Strict/Params-Validate-Strict",
         "finish" : 1761250680.11725,
         "name" : "Params-Validate-Strict",
         "perl" : "5.40.3",
         "run" : "t/alternative.t",
         "start" : 1761250680.11096,
         "version" : "0.20"
      },
      {
         "OS" : "linux",
         "abstract" : "Validates a set of parameters against a schema",
         "dir" : "/home/runner/work/Params-Validate-Strict/Params-Validate-Strict",
         "finish" : 1761250680.51005,
         "name" : "Params-Validate-Strict",
         "perl" : "5.40.3",
         "run" : "t/array.t",
         "start" : 1761250680.50592,
         "version" : "0.20"
      },
      {
         "OS" : "linux",
         "abstract" : "Validates a set of parameters against a schema",
         "dir" : "/home/runner/work/Params-Validate-Strict/Params-Validate-Strict",
         "finish" : 1761250680.87279,
         "name" : "Params-Validate-Strict",
         "perl" : "5.40.3",
         "run" : "t/comment-spelling.t",
         "start" : 1761250680.87261,
         "version" : "0.20"
      },
      {
         "OS" : "linux",
         "abstract" : "Validates a set of parameters against a schema",
         "dir" : "/home/runner/work/Params-Validate-Strict/Params-Validate-Strict",
         "finish" : 1761250681.16334,
         "name" : "Params-Validate-Strict",
         "perl" : "5.40.3",
         "run" : "t/cross_validation.t",
         "start" : 1761250681.13754,
         "version" : "0.20"
      },
      {
         "OS" : "linux",
         "abstract" : "Validates a set of parameters against a schema",
         "dir" : "/home/runner/work/Params-Validate-Strict/Params-Validate-Strict",
         "finish" : 1761250681.63129,
         "name" : "Params-Validate-Strict",
         "perl" : "5.40.3",
         "run" : "t/custom_types.t",
         "start" : 1761250681.60729,
         "version" : "0.20"
      },
      {
         "OS" : "linux",
         "abstract" : "Validates a set of parameters against a schema",
         "dir" : "/home/runner/work/Params-Validate-Strict/Params-Validate-Strict",
         "finish" : 1761250682.05374,
         "name" : "Params-Validate-Strict",
         "perl" : "5.40.3",
         "run" : "t/custom_validation.t",
         "start" : 1761250682.04443,
         "version" : "0.20"
      },
      {
         "OS" : "linux",
         "abstract" : "Validates a set of parameters against a schema",
         "dir" : "/home/runner/work/Params-Validate-Strict/Params-Validate-Strict",
         "finish" : 1761250682.45842,
         "name" : "Params-Validate-Strict",
         "perl" : "5.40.3",
         "run" : "t/default.t",
         "start" : 1761250682.45736,
         "version" : "0.20"
      },
      {
         "OS" : "linux",
         "abstract" : "Validates a set of parameters against a schema",
         "dir" : "/home/runner/work/Params-Validate-Strict/Params-Validate-Strict",
         "finish" : 1761250682.81298,
         "name" : "Params-Validate-Strict",
         "perl" : "5.40.3",
         "run" : "t/eof.t",
         "start" : 1761250682.8128,
         "version" : "0.20"
      },
      {
         "OS" : "linux",
         "abstract" : "Validates a set of parameters against a schema",
         "dir" : "/home/runner/work/Params-Validate-Strict/Params-Validate-Strict",
         "finish" : 1761250683.04331,
         "name" : "Params-Validate-Strict",
         "perl" : "5.40.3",
         "run" : "t/eol.t",
         "start" : 1761250683.04313,
         "version" : "0.20"
      },
      {
         "OS" : "linux",
         "abstract" : "Validates a set of parameters against a schema",
         "dir" : "/home/runner/work/Params-Validate-Strict/Params-Validate-Strict",
         "finish" : 1761250683.30624,
         "name" : "Params-Validate-Strict",
         "perl" : "5.40.3",
         "run" : "t/get.t",
         "start" : 1761250683.30506,
         "version" : "0.20"
      },
      {
         "OS" : "linux",
         "abstract" : "Validates a set of parameters against a schema",
         "dir" : "/home/runner/work/Params-Validate-Strict/Params-Validate-Strict",
         "finish" : 1761250683.70392,
         "name" : "Params-Validate-Strict",
         "perl" : "5.40.3",
         "run" : "t/nested.t",
         "start" : 1761250683.69269,
         "version" : "0.20"
      },
      {
         "OS" : "linux",
         "abstract" : "Validates a set of parameters against a schema",
         "dir" : "/home/runner/work/Params-Validate-Strict/Params-Validate-Strict",
         "finish" : 1761250684.11148,
         "name" : "Params-Validate-Strict",
         "perl" : "5.40.3",
         "run" : "t/notmemberof.t",
         "start" : 1761250684.09142,
         "version" : "0.20"
      },
      {
         "OS" : "linux",
         "abstract" : "Validates a set of parameters against a schema",
         "dir" : "/home/runner/work/Params-Validate-Strict/Params-Validate-Strict",
         "finish" : 1761250684.49217,
         "name" : "Params-Validate-Strict",
         "perl" : "5.40.3",
         "run" : "t/pod-cm.t",
         "start" : 1761250684.49198,
         "version" : "0.20"
      },
      {
         "OS" : "linux",
         "abstract" : "Validates a set of parameters against a schema",
         "dir" : "/home/runner/work/Params-Validate-Strict/Params-Validate-Strict",
         "finish" : 1761250684.72051,
         "name" : "Params-Validate-Strict",
         "perl" : "5.40.3",
         "run" : "t/pod-coverage.t",
         "start" : 1761250684.72029,
         "version" : "0.20"
      },
      {
         "OS" : "linux",
         "abstract" : "Validates a set of parameters against a schema",
         "dir" : "/home/runner/work/Params-Validate-Strict/Params-Validate-Strict",
         "finish" : 1761250684.94671,
         "name" : "Params-Validate-Strict",
         "perl" : "5.40.3",
         "run" : "t/pod-spelling.t",
         "start" : 1761250684.94654,
         "version" : "0.20"
      },
      {
         "OS" : "linux",
         "abstract" : "Validates a set of parameters against a schema",
         "dir" : "/home/runner/work/Params-Validate-Strict/Params-Validate-Strict",
         "finish" : 1761250685.17162,
         "name" : "Params-Validate-Strict",
         "perl" : "5.40.3",
         "run" : "t/pod-synopsis.t",
         "start" : 1761250685.17145,
         "version" : "0.20"
      },
      {
         "OS" : "linux",
         "abstract" : "Validates a set of parameters against a schema",
         "dir" : "/home/runner/work/Params-Validate-Strict/Params-Validate-Strict",
         "finish" : 1761250685.39914,
         "name" : "Params-Validate-Strict",
         "perl" : "5.40.3",
         "run" : "t/pod.t",
         "start" : 1761250685.39896,
         "version" : "0.20"
      },
      {
         "OS" : "linux",
         "abstract" : "Validates a set of parameters against a schema",
         "dir" : "/home/runner/work/Params-Validate-Strict/Params-Validate-Strict",
         "finish" : 1761250685.62619,
         "name" : "Params-Validate-Strict",
         "perl" : "5.40.3",
         "run" : "t/prereq.t",
         "start" : 1761250685.62601,
         "version" : "0.20"
      },
      {
         "OS" : "linux",
         "abstract" : "Validates a set of parameters against a schema",
         "dir" : "/home/runner/work/Params-Validate-Strict/Params-Validate-Strict",
         "finish" : 1761250685.85292,
         "name" : "Params-Validate-Strict",
         "perl" : "5.40.3",
         "run" : "t/strict.t",
         "start" : 1761250685.85274,
         "version" : "0.20"
      },
      {
         "OS" : "linux",
         "abstract" : "Validates a set of parameters against a schema",
         "dir" : "/home/runner/work/Params-Validate-Strict/Params-Validate-Strict",
         "finish" : 1761250686.08112,
         "name" : "Params-Validate-Strict",
         "perl" : "5.40.3",
         "run" : "t/tabs.t",
         "start" : 1761250686.08094,
         "version" : "0.20"
      },
      {
         "OS" : "linux",
         "abstract" : "Validates a set of parameters against a schema",
         "dir" : "/home/runner/work/Params-Validate-Strict/Params-Validate-Strict",
         "finish" : 1761250686.36501,
         "name" : "Params-Validate-Strict",
         "perl" : "5.40.3",
         "run" : "t/transform.t",
         "start" : 1761250686.35071,
         "version" : "0.20"
      },
      {
         "OS" : "linux",
         "abstract" : "Validates a set of parameters against a schema",
         "dir" : "/home/runner/work/Params-Validate-Strict/Params-Validate-Strict",
         "finish" : 1761250686.79139,
         "name" : "Params-Validate-Strict",
         "perl" : "5.40.3",
         "run" : "t/validate.t",
         "start" : 1761250686.78853,
         "version" : "0.20"
      },
      {
         "OS" : "linux",
         "abstract" : "Validates a set of parameters against a schema",
         "dir" : "/home/runner/work/Params-Validate-Strict/Params-Validate-Strict",
         "finish" : 1761250687.14825,
         "name" : "Params-Validate-Strict",
         "perl" : "5.40.3",
         "run" : "t/vars.t",
         "start" : 1761250687.14807,
         "version" : "0.20"
      }
   ],
   "summary" : {
      "Total" : {
         "branch" : {
            "covered" : 304,
            "error" : 88,
            "percentage" : 77.5510204081633,
            "total" : 392,
            "uncoverable" : 0
         },
         "condition" : {
            "covered" : 60,
            "error" : 23,
            "percentage" : 72.289156626506,
            "total" : 83,
            "uncoverable" : 0
         },
         "statement" : {
            "covered" : 328,
            "error" : 85,
            "percentage" : 79.4188861985472,
            "total" : 413
         },
         "subroutine" : {
            "covered" : 14,
            "percentage" : 100,
            "total" : 14
         },
         "total" : {
            "covered" : 706,
            "error" : 196,
            "percentage" : 78.270509977827,
            "total" : 902,
            "uncoverable" : 0
         }
      },
      "blib/lib/Params/Validate/Strict.pm" : {
         "branch" : {
            "covered" : 304,
            "error" : 88,
            "percentage" : 77.5510204081633,
            "total" : 392,
            "uncoverable" : 0
         },
         "condition" : {
            "covered" : 60,
            "error" : 23,
            "percentage" : 72.289156626506,
            "total" : 83,
            "uncoverable" : 0
         },
         "statement" : {
            "covered" : 328,
            "error" : 85,
            "percentage" : 79.4188861985472,
            "total" : 413
         },
         "subroutine" : {
            "covered" : 14,
            "percentage" : 100,
            "total" : 14
         },
         "total" : {
            "covered" : 706,
            "error" : 196,
            "percentage" : 78.270509977827,
            "total" : 902,
            "uncoverable" : 0
         }
      }
   }
}
