{
   "runs" : [
      {
         "OS" : "linux",
         "abstract" : "Validates a set of parameters against a schema",
         "dir" : "/home/runner/work/Params-Validate-Strict/Params-Validate-Strict",
         "finish" : 1778549735.00843,
         "name" : "Params-Validate-Strict",
         "perl" : "5.40.4",
         "run" : "-e",
         "start" : 1778549716.06148,
         "version" : "0.32"
      },
      {
         "OS" : "linux",
         "abstract" : "Validates a set of parameters against a schema",
         "dir" : "/home/runner/work/Params-Validate-Strict/Params-Validate-Strict",
         "finish" : 1778549716.21472,
         "name" : "Params-Validate-Strict",
         "perl" : "5.40.4",
         "run" : "-e",
         "start" : 1778549716.2146,
         "version" : "0.32"
      },
      {
         "OS" : "linux",
         "abstract" : "Validates a set of parameters against a schema",
         "dir" : "/home/runner/work/Params-Validate-Strict/Params-Validate-Strict",
         "finish" : 1778549716.50219,
         "name" : "Params-Validate-Strict",
         "perl" : "5.40.4",
         "run" : "t/00-load.t",
         "start" : 1778549716.50096,
         "version" : "0.32"
      },
      {
         "OS" : "linux",
         "abstract" : "Validates a set of parameters against a schema",
         "dir" : "/home/runner/work/Params-Validate-Strict/Params-Validate-Strict",
         "finish" : 1778549717.12463,
         "name" : "Params-Validate-Strict",
         "perl" : "5.40.4",
         "run" : "t/10-compile.t",
         "start" : 1778549716.95054,
         "version" : "0.32"
      },
      {
         "OS" : "linux",
         "abstract" : "Validates a set of parameters against a schema",
         "dir" : "/home/runner/work/Params-Validate-Strict/Params-Validate-Strict",
         "finish" : 1778549717.44774,
         "name" : "Params-Validate-Strict",
         "perl" : "5.40.4",
         "run" : "t/30-basics.t",
         "start" : 1778549717.41455,
         "version" : "0.32"
      },
      {
         "OS" : "linux",
         "abstract" : "Validates a set of parameters against a schema",
         "dir" : "/home/runner/work/Params-Validate-Strict/Params-Validate-Strict",
         "finish" : 1778549718.11704,
         "name" : "Params-Validate-Strict",
         "perl" : "5.40.4",
         "run" : "t/40-more.t",
         "start" : 1778549717.98236,
         "version" : "0.32"
      },
      {
         "OS" : "linux",
         "abstract" : "Validates a set of parameters against a schema",
         "dir" : "/home/runner/work/Params-Validate-Strict/Params-Validate-Strict",
         "finish" : 1778549718.87255,
         "name" : "Params-Validate-Strict",
         "perl" : "5.40.4",
         "run" : "t/50-even-more.t",
         "start" : 1778549718.82644,
         "version" : "0.32"
      },
      {
         "OS" : "linux",
         "abstract" : "Validates a set of parameters against a schema",
         "dir" : "/home/runner/work/Params-Validate-Strict/Params-Validate-Strict",
         "finish" : 1778549719.58985,
         "name" : "Params-Validate-Strict",
         "perl" : "5.40.4",
         "run" : "t/60-most.t",
         "start" : 1778549719.43324,
         "version" : "0.32"
      },
      {
         "OS" : "linux",
         "abstract" : "Validates a set of parameters against a schema",
         "dir" : "/home/runner/work/Params-Validate-Strict/Params-Validate-Strict",
         "finish" : 1778549720.27082,
         "name" : "Params-Validate-Strict",
         "perl" : "5.40.4",
         "run" : "t/70-more.t",
         "start" : 1778549720.24355,
         "version" : "0.32"
      },
      {
         "OS" : "linux",
         "abstract" : "Validates a set of parameters against a schema",
         "dir" : "/home/runner/work/Params-Validate-Strict/Params-Validate-Strict",
         "finish" : 1778549720.79381,
         "name" : "Params-Validate-Strict",
         "perl" : "5.40.4",
         "run" : "t/alternative.t",
         "start" : 1778549720.7871,
         "version" : "0.32"
      },
      {
         "OS" : "linux",
         "abstract" : "Validates a set of parameters against a schema",
         "dir" : "/home/runner/work/Params-Validate-Strict/Params-Validate-Strict",
         "finish" : 1778549721.29378,
         "name" : "Params-Validate-Strict",
         "perl" : "5.40.4",
         "run" : "t/array.t",
         "start" : 1778549721.28891,
         "version" : "0.32"
      },
      {
         "OS" : "linux",
         "abstract" : "Validates a set of parameters against a schema",
         "dir" : "/home/runner/work/Params-Validate-Strict/Params-Validate-Strict",
         "finish" : 1778549721.7414,
         "name" : "Params-Validate-Strict",
         "perl" : "5.40.4",
         "run" : "t/comment-spelling.t",
         "start" : 1778549721.74117,
         "version" : "0.32"
      },
      {
         "OS" : "linux",
         "abstract" : "Validates a set of parameters against a schema",
         "dir" : "/home/runner/work/Params-Validate-Strict/Params-Validate-Strict",
         "finish" : 1778549722.04808,
         "name" : "Params-Validate-Strict",
         "perl" : "5.40.4",
         "run" : "t/cross_validation.t",
         "start" : 1778549722.02344,
         "version" : "0.32"
      },
      {
         "OS" : "linux",
         "abstract" : "Validates a set of parameters against a schema",
         "dir" : "/home/runner/work/Params-Validate-Strict/Params-Validate-Strict",
         "finish" : 1778549722.62949,
         "name" : "Params-Validate-Strict",
         "perl" : "5.40.4",
         "run" : "t/custom_types.t",
         "start" : 1778549722.60196,
         "version" : "0.32"
      },
      {
         "OS" : "linux",
         "abstract" : "Validates a set of parameters against a schema",
         "dir" : "/home/runner/work/Params-Validate-Strict/Params-Validate-Strict",
         "finish" : 1778549723.17396,
         "name" : "Params-Validate-Strict",
         "perl" : "5.40.4",
         "run" : "t/custom_validation.t",
         "start" : 1778549723.16345,
         "version" : "0.32"
      },
      {
         "OS" : "linux",
         "abstract" : "Validates a set of parameters against a schema",
         "dir" : "/home/runner/work/Params-Validate-Strict/Params-Validate-Strict",
         "finish" : 1778549723.69919,
         "name" : "Params-Validate-Strict",
         "perl" : "5.40.4",
         "run" : "t/default.t",
         "start" : 1778549723.69775,
         "version" : "0.32"
      },
      {
         "OS" : "linux",
         "abstract" : "Validates a set of parameters against a schema",
         "dir" : "/home/runner/work/Params-Validate-Strict/Params-Validate-Strict",
         "finish" : 1778549724.37386,
         "name" : "Params-Validate-Strict",
         "perl" : "5.40.4",
         "run" : "t/edge_cases.t",
         "start" : 1778549724.20476,
         "version" : "0.32"
      },
      {
         "OS" : "linux",
         "abstract" : "Validates a set of parameters against a schema",
         "dir" : "/home/runner/work/Params-Validate-Strict/Params-Validate-Strict",
         "finish" : 1778549725.00859,
         "name" : "Params-Validate-Strict",
         "perl" : "5.40.4",
         "run" : "t/eof.t",
         "start" : 1778549725.00816,
         "version" : "0.32"
      },
      {
         "OS" : "linux",
         "abstract" : "Validates a set of parameters against a schema",
         "dir" : "/home/runner/work/Params-Validate-Strict/Params-Validate-Strict",
         "finish" : 1778549725.25197,
         "name" : "Params-Validate-Strict",
         "perl" : "5.40.4",
         "run" : "t/eol.t",
         "start" : 1778549725.25169,
         "version" : "0.32"
      },
      {
         "OS" : "linux",
         "abstract" : "Validates a set of parameters against a schema",
         "dir" : "/home/runner/work/Params-Validate-Strict/Params-Validate-Strict",
         "finish" : 1778549725.73474,
         "name" : "Params-Validate-Strict",
         "perl" : "5.40.4",
         "run" : "t/extended_tests.t",
         "start" : 1778549725.54772,
         "version" : "0.32"
      },
      {
         "OS" : "linux",
         "abstract" : "Validates a set of parameters against a schema",
         "dir" : "/home/runner/work/Params-Validate-Strict/Params-Validate-Strict",
         "finish" : 1778549726.68135,
         "name" : "Params-Validate-Strict",
         "perl" : "5.40.4",
         "run" : "t/function.t",
         "start" : 1778549726.44672,
         "version" : "0.32"
      },
      {
         "OS" : "linux",
         "abstract" : "Validates a set of parameters against a schema",
         "dir" : "/home/runner/work/Params-Validate-Strict/Params-Validate-Strict",
         "finish" : 1778549727.38166,
         "name" : "Params-Validate-Strict",
         "perl" : "5.40.4",
         "run" : "t/get.t",
         "start" : 1778549727.38003,
         "version" : "0.32"
      },
      {
         "OS" : "linux",
         "abstract" : "Validates a set of parameters against a schema",
         "dir" : "/home/runner/work/Params-Validate-Strict/Params-Validate-Strict",
         "finish" : 1778549728.00462,
         "name" : "Params-Validate-Strict",
         "perl" : "5.40.4",
         "run" : "t/integration.t",
         "start" : 1778549727.88496,
         "version" : "0.32"
      },
      {
         "OS" : "linux",
         "abstract" : "Validates a set of parameters against a schema",
         "dir" : "/home/runner/work/Params-Validate-Strict/Params-Validate-Strict",
         "finish" : 1778549728.66476,
         "name" : "Params-Validate-Strict",
         "perl" : "5.40.4",
         "run" : "t/memberof.t",
         "start" : 1778549728.63636,
         "version" : "0.32"
      },
      {
         "OS" : "linux",
         "abstract" : "Validates a set of parameters against a schema",
         "dir" : "/home/runner/work/Params-Validate-Strict/Params-Validate-Strict",
         "finish" : 1778549729.22179,
         "name" : "Params-Validate-Strict",
         "perl" : "5.40.4",
         "run" : "t/nested.t",
         "start" : 1778549729.20866,
         "version" : "0.32"
      },
      {
         "OS" : "linux",
         "abstract" : "Validates a set of parameters against a schema",
         "dir" : "/home/runner/work/Params-Validate-Strict/Params-Validate-Strict",
         "finish" : 1778549729.74341,
         "name" : "Params-Validate-Strict",
         "perl" : "5.40.4",
         "run" : "t/notmemberof.t",
         "start" : 1778549729.72175,
         "version" : "0.32"
      },
      {
         "OS" : "linux",
         "abstract" : "Validates a set of parameters against a schema",
         "dir" : "/home/runner/work/Params-Validate-Strict/Params-Validate-Strict",
         "finish" : 1778549730.23285,
         "name" : "Params-Validate-Strict",
         "perl" : "5.40.4",
         "run" : "t/pod-cm.t",
         "start" : 1778549730.23255,
         "version" : "0.32"
      },
      {
         "OS" : "linux",
         "abstract" : "Validates a set of parameters against a schema",
         "dir" : "/home/runner/work/Params-Validate-Strict/Params-Validate-Strict",
         "finish" : 1778549730.46938,
         "name" : "Params-Validate-Strict",
         "perl" : "5.40.4",
         "run" : "t/pod-coverage.t",
         "start" : 1778549730.46907,
         "version" : "0.32"
      },
      {
         "OS" : "linux",
         "abstract" : "Validates a set of parameters against a schema",
         "dir" : "/home/runner/work/Params-Validate-Strict/Params-Validate-Strict",
         "finish" : 1778549730.70556,
         "name" : "Params-Validate-Strict",
         "perl" : "5.40.4",
         "run" : "t/pod-spelling.t",
         "start" : 1778549730.70524,
         "version" : "0.32"
      },
      {
         "OS" : "linux",
         "abstract" : "Validates a set of parameters against a schema",
         "dir" : "/home/runner/work/Params-Validate-Strict/Params-Validate-Strict",
         "finish" : 1778549730.94114,
         "name" : "Params-Validate-Strict",
         "perl" : "5.40.4",
         "run" : "t/pod-synopsis.t",
         "start" : 1778549730.94088,
         "version" : "0.32"
      },
      {
         "OS" : "linux",
         "abstract" : "Validates a set of parameters against a schema",
         "dir" : "/home/runner/work/Params-Validate-Strict/Params-Validate-Strict",
         "finish" : 1778549731.17868,
         "name" : "Params-Validate-Strict",
         "perl" : "5.40.4",
         "run" : "t/pod.t",
         "start" : 1778549731.17839,
         "version" : "0.32"
      },
      {
         "OS" : "linux",
         "abstract" : "Validates a set of parameters against a schema",
         "dir" : "/home/runner/work/Params-Validate-Strict/Params-Validate-Strict",
         "finish" : 1778549731.46648,
         "name" : "Params-Validate-Strict",
         "perl" : "5.40.4",
         "run" : "t/positional.t",
         "start" : 1778549731.46425,
         "version" : "0.32"
      },
      {
         "OS" : "linux",
         "abstract" : "Validates a set of parameters against a schema",
         "dir" : "/home/runner/work/Params-Validate-Strict/Params-Validate-Strict",
         "finish" : 1778549731.91966,
         "name" : "Params-Validate-Strict",
         "perl" : "5.40.4",
         "run" : "t/prereq.t",
         "start" : 1778549731.91937,
         "version" : "0.32"
      },
      {
         "OS" : "linux",
         "abstract" : "Validates a set of parameters against a schema",
         "dir" : "/home/runner/work/Params-Validate-Strict/Params-Validate-Strict",
         "finish" : 1778549732.15756,
         "name" : "Params-Validate-Strict",
         "perl" : "5.40.4",
         "run" : "t/strict.t",
         "start" : 1778549732.15726,
         "version" : "0.32"
      },
      {
         "OS" : "linux",
         "abstract" : "Validates a set of parameters against a schema",
         "dir" : "/home/runner/work/Params-Validate-Strict/Params-Validate-Strict",
         "finish" : 1778549732.43566,
         "name" : "Params-Validate-Strict",
         "perl" : "5.40.4",
         "run" : "t/t_union_type.t",
         "start" : 1778549732.41817,
         "version" : "0.32"
      },
      {
         "OS" : "linux",
         "abstract" : "Validates a set of parameters against a schema",
         "dir" : "/home/runner/work/Params-Validate-Strict/Params-Validate-Strict",
         "finish" : 1778549732.96725,
         "name" : "Params-Validate-Strict",
         "perl" : "5.40.4",
         "run" : "t/transform.t",
         "start" : 1778549732.94933,
         "version" : "0.32"
      },
      {
         "OS" : "linux",
         "abstract" : "Validates a set of parameters against a schema",
         "dir" : "/home/runner/work/Params-Validate-Strict/Params-Validate-Strict",
         "finish" : 1778549733.76701,
         "name" : "Params-Validate-Strict",
         "perl" : "5.40.4",
         "run" : "t/unit.t",
         "start" : 1778549733.50651,
         "version" : "0.32"
      },
      {
         "OS" : "linux",
         "abstract" : "Validates a set of parameters against a schema",
         "dir" : "/home/runner/work/Params-Validate-Strict/Params-Validate-Strict",
         "finish" : 1778549734.52149,
         "name" : "Params-Validate-Strict",
         "perl" : "5.40.4",
         "run" : "t/validate.t",
         "start" : 1778549734.51801,
         "version" : "0.32"
      },
      {
         "OS" : "linux",
         "abstract" : "Validates a set of parameters against a schema",
         "dir" : "/home/runner/work/Params-Validate-Strict/Params-Validate-Strict",
         "finish" : 1778549734.96879,
         "name" : "Params-Validate-Strict",
         "perl" : "5.40.4",
         "run" : "t/vars.t",
         "start" : 1778549734.96853,
         "version" : "0.32"
      }
   ],
   "summary" : {
      "Total" : {
         "branch" : {
            "covered" : 509,
            "error" : 85,
            "percentage" : 85.6902356902357,
            "total" : 594,
            "uncoverable" : 0
         },
         "condition" : {
            "covered" : 200,
            "error" : 66,
            "percentage" : 75.187969924812,
            "total" : 266,
            "uncoverable" : 0
         },
         "statement" : {
            "covered" : 579,
            "error" : 94,
            "percentage" : 86.0326894502229,
            "total" : 673
         },
         "subroutine" : {
            "covered" : 27,
            "percentage" : 100,
            "total" : 27
         },
         "total" : {
            "covered" : 1315,
            "error" : 245,
            "percentage" : 84.2948717948718,
            "total" : 1560,
            "uncoverable" : 0
         }
      },
      "blib/lib/Params/Validate/Strict.pm" : {
         "branch" : {
            "covered" : 509,
            "error" : 85,
            "percentage" : 85.6902356902357,
            "total" : 594,
            "uncoverable" : 0
         },
         "condition" : {
            "covered" : 200,
            "error" : 66,
            "percentage" : 75.187969924812,
            "total" : 266,
            "uncoverable" : 0
         },
         "statement" : {
            "covered" : 579,
            "error" : 94,
            "percentage" : 86.0326894502229,
            "total" : 673
         },
         "subroutine" : {
            "covered" : 27,
            "percentage" : 100,
            "total" : 27
         },
         "total" : {
            "covered" : 1315,
            "error" : 245,
            "percentage" : 84.2948717948718,
            "total" : 1560,
            "uncoverable" : 0
         }
      }
   }
}
